ctm_mcp_server/LICENSE
ctm_mcp_server/README.md
ctm_mcp_server/__init__.py
ctm_mcp_server/stdio_server.py
ctm_mcp_server/data/__init__.py
ctm_mcp_server/data/cache.py
ctm_mcp_server/data/git_repo.py
ctm_mcp_server/data/github_client.py
ctm_mcp_server/models/__init__.py
ctm_mcp_server/models/git_models.py
ctm_mcp_server/models/github_models.py
ctm_mcp_server/models/result_models.py
ctm_mcp_server/models/symbol_models.py
ctm_mcp_server/parsing/__init__.py
ctm_mcp_server/parsing/parser.py
ctm_mcp_server/parsing/extractors/__init__.py
ctm_mcp_server/utils/__init__.py
ctm_mcp_server/utils/decorators.py
ctm_mcp_server/utils/tool_helpers.py
codebase_time_machine-0.1.2.dist-info/METADATA
codebase_time_machine-0.1.2.dist-info/WHEEL
codebase_time_machine-0.1.2.dist-info/entry_points.txt
codebase_time_machine-0.1.2.dist-info/RECORD
